eventcalendar/__init__.py
eventcalendar/asgi.py
eventcalendar/helper.py
eventcalendar/settings.py
eventcalendar/urls.py
eventcalendar/views.py
eventcalendar/wsgi.py
opcalendar/__init__.py
opcalendar/admin.py
opcalendar/app_settings.py
opcalendar/apps.py
opcalendar/auth_hooks.py
opcalendar/calendar.py
opcalendar/decorators.py
opcalendar/forms.py
opcalendar/helpers.py
opcalendar/models.py
opcalendar/providers.py
opcalendar/signals.py
opcalendar/swagger.json
opcalendar/tasks.py
opcalendar/urls.py
opcalendar/utils.py
opcalendar/views.py
opcalendar/cogs/ops.py
opcalendar/migrations/0001_initial.py
opcalendar/migrations/0002_auto_20201104_1054.py
opcalendar/migrations/0003_eventhost.py
opcalendar/migrations/0004_event_host.py
opcalendar/migrations/0005_auto_20201104_1127.py
opcalendar/migrations/0006_auto_20201104_1201.py
opcalendar/migrations/0007_eventhost_twitter.py
opcalendar/migrations/0008_auto_20201105_0846.py
opcalendar/migrations/0009_auto_20201105_0859.py
opcalendar/migrations/0010_auto_20201105_1602.py
opcalendar/migrations/0011_eventimport.py
opcalendar/migrations/0012_auto_20210112_0934.py
opcalendar/migrations/0013_eventimport_creator.py
opcalendar/migrations/0014_auto_20210113_0836.py
opcalendar/migrations/0015_eventimport_eve_character.py
opcalendar/migrations/0016_auto_20210119_1545.py
opcalendar/migrations/0017_auto_20210119_1626.py
opcalendar/migrations/0018_auto_20210119_1701.py
opcalendar/migrations/0019_auto_20210125_1005.py
opcalendar/migrations/0020_auto_20210125_1007.py
opcalendar/migrations/0021_eventhost_logo_url.py
opcalendar/migrations/0022_auto_20210222_1255.py
opcalendar/migrations/0023_auto_20210330_0632.py
opcalendar/migrations/0024_auto_20210429_1111.py
opcalendar/migrations/0025_auto_20220115_1101.py
opcalendar/migrations/0026_alter_event_repeat_event.py
opcalendar/migrations/__init__.py
opcalendar/static/opcalendar/calendar.png
opcalendar/static/opcalendar/style_dark.css
opcalendar/static/opcalendar/style_light.css
aa_opcalendar-2.4.0.dist-info/LICENSE
aa_opcalendar-2.4.0.dist-info/METADATA
aa_opcalendar-2.4.0.dist-info/WHEEL
aa_opcalendar-2.4.0.dist-info/top_level.txt
aa_opcalendar-2.4.0.dist-info/RECORD
