Metadata-Version: 2.1
Name: aa-opcalendar
Version: 2.4.0
Summary: Event calendar plugin app for Alliance Auth
Home-page: https://gitlab.com/paulipa/allianceauth-opcalendar
Author: Ikarus Cesaille
Author-email: contact@eve-linknet.com
License: MIT
Classifier: Environment :: Web Environment
Classifier: Framework :: Django
Classifier: Framework :: Django :: 2.2
Classifier: Intended Audience :: Developers
Classifier: License :: OSI Approved :: MIT License
Classifier: Operating System :: OS Independent
Classifier: Programming Language :: Python
Classifier: Programming Language :: Python :: 3.5
Classifier: Topic :: Internet :: WWW/HTTP
Classifier: Topic :: Internet :: WWW/HTTP :: Dynamic Content
License-File: LICENSE
Requires-Dist: allianceauth (>=2.8.0)
Requires-Dist: feedparser
Requires-Dist: ics (>=0.7.2)
Requires-Dist: pytz
Requires-Dist: django-ical
